payequity/Audit.py
payequity/JobGroup.py
payequity/JobGroupEnssemble.py
payequity/Regressor.py
payequity/__init__.py
payequity/version.py
payequity/tests/__init__.py
payequity/tests/test_audit.py
payequity/tests/test_job_group.py
payequity/tests/test_job_group_enssemble.py
payequity/tests/test_regressor.py
PayEquity-0.1.6.dist-info/LICENSE.txt
PayEquity-0.1.6.dist-info/METADATA
PayEquity-0.1.6.dist-info/WHEEL
PayEquity-0.1.6.dist-info/top_level.txt
PayEquity-0.1.6.dist-info/RECORD
