Metadata-Version: 2.1
Name: PayEquity
Version: 0.1.6
Summary: Pay Equity Library
Home-page: https://github.com/scunden/pay-equity
Author: Steven Cunden
Author-email: slcunden@gmail.com
License: MIT
License-File: LICENSE.txt
Requires-Dist: numpy
Requires-Dist: pandas
